setup.py
pysk/__init__.py
pysk/pysk.py
pysk.egg-info/PKG-INFO
pysk.egg-info/SOURCES.txt
pysk.egg-info/dependency_links.txt
pysk.egg-info/entry_points.txt
pysk.egg-info/requires.txt
pysk.egg-info/top_level.txt