Metadata-Version: 1.0
Name: pysk
Version: 0.0.2
Summary: client application to display streaming data from a signalk server via curses and other user interfaces
Home-page: https://github.com/ph1l/pysk
Author: Philip J Freeman
Author-email: elektron@halo.nu
License: GPL3
Keywords: signalk curses
Platform: UNKNOWN
